PseudoNetCDF/ArrayTransforms.py
PseudoNetCDF/MetaNetCDF.py
PseudoNetCDF/__init__.py
PseudoNetCDF/_getreader.py
PseudoNetCDF/_getwriter.py
PseudoNetCDF/coordutil.py
PseudoNetCDF/net_balance.py
PseudoNetCDF/netcdf.py
PseudoNetCDF/pncdump.py
PseudoNetCDF/pnceval.py
PseudoNetCDF/pncgen.py
PseudoNetCDF/pncload.py
PseudoNetCDF/pncparse.py
PseudoNetCDF/pncview.py
PseudoNetCDF/pncwarn.py
PseudoNetCDF/register.py
PseudoNetCDF/sci_var.py
PseudoNetCDF/units.py
PseudoNetCDF/userfuncs.py
PseudoNetCDF/version.py
PseudoNetCDF/xarray_plugin.py
PseudoNetCDF/aermodfiles/__init__.py
PseudoNetCDF/aermodfiles/_aermod_plotfile.py
PseudoNetCDF/aermodfiles/.ipynb_checkpoints/_aermod_plotfile-checkpoint.py
PseudoNetCDF/camxfiles/ArrayTransforms.py
PseudoNetCDF/camxfiles/FortranFileUtil.py
PseudoNetCDF/camxfiles/Memmaps.py
PseudoNetCDF/camxfiles/Readers.py
PseudoNetCDF/camxfiles/Writers.py
PseudoNetCDF/camxfiles/__init__.py
PseudoNetCDF/camxfiles/aerosol_names.py
PseudoNetCDF/camxfiles/timetuple.py
PseudoNetCDF/camxfiles/units.py
PseudoNetCDF/camxfiles/util.py
PseudoNetCDF/camxfiles/cloud_rain/Memmap.py
PseudoNetCDF/camxfiles/cloud_rain/Transforms.py
PseudoNetCDF/camxfiles/cloud_rain/Write.py
PseudoNetCDF/camxfiles/cloud_rain/__init__.py
PseudoNetCDF/camxfiles/finst/Memmap.py
PseudoNetCDF/camxfiles/finst/__init__.py
PseudoNetCDF/camxfiles/height_pressure/Memmap.py
PseudoNetCDF/camxfiles/height_pressure/Read.py
PseudoNetCDF/camxfiles/height_pressure/Transforms.py
PseudoNetCDF/camxfiles/height_pressure/Write.py
PseudoNetCDF/camxfiles/height_pressure/__init__.py
PseudoNetCDF/camxfiles/humidity/Memmap.py
PseudoNetCDF/camxfiles/humidity/Read.py
PseudoNetCDF/camxfiles/humidity/Transforms.py
PseudoNetCDF/camxfiles/humidity/Write.py
PseudoNetCDF/camxfiles/humidity/__init__.py
PseudoNetCDF/camxfiles/ipr/Memmap.py
PseudoNetCDF/camxfiles/ipr/Read.py
PseudoNetCDF/camxfiles/ipr/__init__.py
PseudoNetCDF/camxfiles/irr/Memmap.py
PseudoNetCDF/camxfiles/irr/Read.py
PseudoNetCDF/camxfiles/irr/__init__.py
PseudoNetCDF-3.4.1.dist-info/LICENSE
PseudoNetCDF-3.4.1.dist-info/METADATA
PseudoNetCDF-3.4.1.dist-info/WHEEL
PseudoNetCDF-3.4.1.dist-info/entry_points.txt
PseudoNetCDF-3.4.1.dist-info/top_level.txt
PseudoNetCDF-3.4.1.dist-info/RECORD
