Metadata-Version: 2.1
Name: PseudoNetCDF
Version: 3.4.1
Summary: Like NetCDF and NCO, but works with NetCDF and other scientific formats.
Home-page: http://github.com/barronh/pseudonetcdf/
Author: Barron Henderson
Author-email: barronh@gmail.com
Maintainer: Barron Henderson
Maintainer-email: barronh@gmail.com
Classifier: Programming Language :: Python :: 2.7
Classifier: Programming Language :: Python :: 3
Classifier: Operating System :: MacOS
Classifier: Operating System :: Microsoft :: Windows
Classifier: Operating System :: POSIX
Classifier: Topic :: Scientific/Engineering
Classifier: Topic :: Scientific/Engineering :: Atmospheric Science
License-File: LICENSE
Requires-Dist: numpy >=1.2
Requires-Dist: netCDF4
Requires-Dist: scipy
Requires-Dist: matplotlib
Requires-Dist: pyyaml
Requires-Dist: pandas
Provides-Extra: mapping
Requires-Dist: basemap ; extra == 'mapping'
Provides-Extra: projections
Requires-Dist: pyproj ; extra == 'projections'
Provides-Extra: textfiles
Requires-Dist: pandas ; extra == 'textfiles'
